{
  "total_self_ms": 120518.58135900018,
  "distinct_spans": 130,
  "spans": [
    {
      "name": "reduce_dense",
      "count": 2373,
      "total_ms": 31892.269595000016,
      "self_ms": 28770.678519000074,
      "mean_total_us": 13439.641632954073
    },
    {
      "name": "interpolate_inplace",
      "count": 17416,
      "total_ms": 19204.424079998724,
      "self_ms": 19204.424079998724,
      "mean_total_us": 1102.688566835021
    },
    {
      "name": "CpuBackend::gruen_segmented_reduce",
      "count": 16,
      "total_ms": 18137.602292000014,
      "self_ms": 18137.602292000014,
      "mean_total_us": 1133600.143250001
    },
    {
      "name": "multi_pair_g2_setup_parallel",
      "count": 62,
      "total_ms": 16542.731164999957,
      "self_ms": 12443.188706999961,
      "mean_total_us": 266818.24459677347
    },
    {
      "name": "CpuBackend::eq_project",
      "count": 82,
      "total_ms": 9880.534627000005,
      "self_ms": 9815.789247999935,
      "mean_total_us": 120494.32471951224
    },
    {
      "name": "derived::ram_val",
      "count": 1,
      "total_ms": 6876.555791999999,
      "self_ms": 6876.555791999999,
      "mean_total_us": 6876555.791999999
    },
    {
      "name": "derived::ram_ra_indicator",
      "count": 2,
      "total_ms": 4950.491292000011,
      "self_ms": 4950.491292000011,
      "mean_total_us": 2475245.6460000053
    },
    {
      "name": "G1::msm",
      "count": 43043,
      "total_ms": 3061.2648330001107,
      "self_ms": 3061.2648330001107,
      "mean_total_us": 71.12108433427295
    },
    {
      "name": "Commit",
      "count": 3,
      "total_ms": 2975.238291000001,
      "self_ms": 2974.920036999995,
      "mean_total_us": 991746.0970000004
    },
    {
      "name": "CpuBackend::segmented_reduce",
      "count": 16,
      "total_ms": 2878.923790999994,
      "self_ms": 2878.923790999994,
      "mean_total_us": 179932.7369374996
    },
    {
      "name": "derived::ram_combined_ra",
      "count": 1,
      "total_ms": 2596.761083999999,
      "self_ms": 2596.761083999999,
      "mean_total_us": 2596761.083999999
    },
    {
      "name": "ReduceOpenings",
      "count": 1,
      "total_ms": 2287.5259170000104,
      "self_ms": 1591.9902069999725,
      "mean_total_us": 2287525.9170000106
    },
    {
      "name": "DoryScheme::commit",
      "count": 42,
      "total_ms": 20743.85757999999,
      "self_ms": 1319.5613279998786,
      "mean_total_us": 493901.3709523807
    },
    {
      "name": "Program::build_with_features",
      "count": 2,
      "total_ms": 823.896042,
      "self_ms": 823.896042,
      "mean_total_us": 411948.021
    },
    {
      "name": "multi_pair_parallel",
      "count": 50,
      "total_ms": 731.67953699994,
      "self_ms": 731.67953699994,
      "mean_total_us": 14633.5907399988
    },
    {
      "name": "rlc_combine",
      "count": 1,
      "total_ms": 695.5225,
      "self_ms": 695.5225,
      "mean_total_us": 695522.5
    },
    {
      "name": "DoryProverState::apply_first_challenge",
      "count": 10,
      "total_ms": 616.4514610000103,
      "self_ms": 616.4514610000103,
      "mean_total_us": 61645.14610000104
    },
    {
      "name": "CpuBackend::transpose_from_host",
      "count": 40,
      "total_ms": 502.9447069999874,
      "self_ms": 502.9447069999874,
      "mean_total_us": 12573.617674999685
    },
    {
      "name": "DoryScheme::setup_prover",
      "count": 1,
      "total_ms": 375.058667,
      "self_ms": 375.058667,
      "mean_total_us": 375058.667
    },
    {
      "name": "DoryProverState::apply_second_challenge",
      "count": 10,
      "total_ms": 302.4667100000232,
      "self_ms": 302.4667100000232,
      "mean_total_us": 30246.671000002323
    },
    {
      "name": "create_evaluation_proof",
      "count": 1,
      "total_ms": 1622.1266669999957,
      "self_ms": 276.870494999975,
      "mean_total_us": 1622126.6669999957
    },
    {
      "name": "mb::EqProject",
      "count": 82,
      "total_ms": 14959.540213000037,
      "self_ms": 128.43038100013882,
      "mean_total_us": 182433.41723170778
    },
    {
      "name": "reduce_domain",
      "count": 2,
      "total_ms": 125.90608300000056,
      "self_ms": 125.90608300000056,
      "mean_total_us": 62953.04150000028
    },
    {
      "name": "r1cs::Az",
      "count": 1,
      "total_ms": 120.19420800000057,
      "self_ms": 120.19420800000057,
      "mean_total_us": 120194.20800000057
    },
    {
      "name": "SuffixScatter",
      "count": 16,
      "total_ms": 120.14216800001263,
      "self_ms": 120.14216800001263,
      "mean_total_us": 7508.88550000079
    },
    {
      "name": "QBufferScatter",
      "count": 16,
      "total_ms": 97.78896000000834,
      "self_ms": 97.78896000000834,
      "mean_total_us": 6111.8100000005215
    },
    {
      "name": "derived::reg_val",
      "count": 1,
      "total_ms": 97.42875,
      "self_ms": 97.42875,
      "mean_total_us": 97428.75
    },
    {
      "name": "ReadCheckingReduce",
      "count": 128,
      "total_ms": 96.71508000002801,
      "self_ms": 96.71508000002801,
      "mean_total_us": 755.5865625002189
    },
    {
      "name": "EqPolynomial::evals",
      "count": 94,
      "total_ms": 74.24042100007831,
      "self_ms": 74.24042100007831,
      "mean_total_us": 789.7917127667906
    },
    {
      "name": "G2::msm",
      "count": 30,
      "total_ms": 69.30929400002957,
      "self_ms": 69.30929400002957,
      "mean_total_us": 2310.3098000009854
    },
    {
      "name": "r1cs::Bz",
      "count": 1,
      "total_ms": 68.22920899999886,
      "self_ms": 68.22920899999886,
      "mean_total_us": 68229.20899999887
    },
    {
      "name": "multi_pair_g1_setup_parallel",
      "count": 18,
      "total_ms": 65.03158399999141,
      "self_ms": 65.03158399999141,
      "mean_total_us": 3612.865777777301
    },
    {
      "name": "LagrangeProject",
      "count": 2,
      "total_ms": 58.502291999999436,
      "self_ms": 58.502291999999436,
      "mean_total_us": 29251.145999999717
    },
    {
      "name": "RegroupConstraints",
      "count": 1,
      "total_ms": 245.59145800000056,
      "self_ms": 57.117833000000566,
      "mean_total_us": 245591.45800000057
    },
    {
      "name": "r1cs::Variable",
      "count": 51,
      "total_ms": 54.8709970000051,
      "self_ms": 54.8709970000051,
      "mean_total_us": 1075.9019019608843
    },
    {
      "name": "CpuBackend::eq_table",
      "count": 68,
      "total_ms": 49.78508100001142,
      "self_ms": 49.78508100001142,
      "mean_total_us": 732.133544117815
    },
    {
      "name": "derived::reg_rs2_ra",
      "count": 1,
      "total_ms": 31.59783299998939,
      "self_ms": 31.59783299998939,
      "mean_total_us": 31597.83299998939
    },
    {
      "name": "derived::reg_rs1_ra",
      "count": 1,
      "total_ms": 27.24245800000429,
      "self_ms": 27.24245800000429,
      "mean_total_us": 27242.45800000429
    },
    {
      "name": "derived::reg_rd_wa",
      "count": 1,
      "total_ms": 26.51516599999368,
      "self_ms": 26.51516599999368,
      "mean_total_us": 26515.165999993682
    },
    {
      "name": "WeightedSum",
      "count": 5,
      "total_ms": 24.62070900000632,
      "self_ms": 24.445502999931573,
      "mean_total_us": 4924.141800001264
    },
    {
      "name": "derived::ram_gather_index",
      "count": 1,
      "total_ms": 19.24175,
      "self_ms": 19.24175,
      "mean_total_us": 19241.75
    },
    {
      "name": "UpdateInstanceWeights",
      "count": 15,
      "total_ms": 18.364709000006318,
      "self_ms": 18.364709000006318,
      "mean_total_us": 1224.3139333337544
    },
    {
      "name": "Bind",
      "count": 176,
      "total_ms": 152.92053799999877,
      "self_ms": 16.719380000784994,
      "mean_total_us": 868.8666931818112
    },
    {
      "name": "BatchRoundBegin",
      "count": 246,
      "total_ms": 11.902534999970346,
      "self_ms": 11.902534999970346,
      "mean_total_us": 48.384288617765634
    },
    {
      "name": "MaterializeRA",
      "count": 1,
      "total_ms": 11.902167000010609,
      "self_ms": 11.902167000010609,
      "mean_total_us": 11902.16700001061
    },
    {
      "name": "CollectOpeningClaimAt",
      "count": 42,
      "total_ms": 11.676372999966144,
      "self_ms": 11.674663999959826,
      "mean_total_us": 278.0088809515749
    },
    {
      "name": "AbsorbRoundPoly",
      "count": 265,
      "total_ms": 9.578324999909848,
      "self_ms": 9.578324999909848,
      "mean_total_us": 36.144622641169235
    },
    {
      "name": "stage",
      "count": 8,
      "total_ms": 76913.60204099999,
      "self_ms": 9.092148999683559,
      "mean_total_us": 9614200.255125
    },
    {
      "name": "derived::lookup_table_flag",
      "count": 41,
      "total_ms": 7.258498999997974,
      "self_ms": 7.258498999997974,
      "mean_total_us": 177.03656097556032
    },
    {
      "name": "InstanceBind",
      "count": 319,
      "total_ms": 19100.737241999985,
      "self_ms": 6.996905000500381,
      "mean_total_us": 59876.919253918444
    },
    {
      "name": "CpuBackend::eq_pushforward",
      "count": 5,
      "total_ms": 13.73895799997449,
      "self_ms": 6.195207999974489,
      "mean_total_us": 2747.7915999948978
    },
    {
      "name": "CpuBackend::eq_plus_one_table",
      "count": 2,
      "total_ms": 5.37608299998939,
      "self_ms": 5.37608299998939,
      "mean_total_us": 2688.041499994695
    },
    {
      "name": "trace",
      "count": 1,
      "total_ms": 5.559125,
      "self_ms": 5.178707999999984,
      "mean_total_us": 5559.125
    },
    {
      "name": "BatchAccumulateInstance",
      "count": 468,
      "total_ms": 5.025367999851704,
      "self_ms": 5.025367999851704,
      "mean_total_us": 10.73796581164894
    },
    {
      "name": "mb::upload",
      "count": 38,
      "total_ms": 4.689583999950439,
      "self_ms": 4.689583999950439,
      "mean_total_us": 123.41010526185364
    },
    {
      "name": "CpuBackend::lt_table",
      "count": 2,
      "total_ms": 3.4021659999936817,
      "self_ms": 3.4021659999936817,
      "mean_total_us": 1701.082999996841
    },
    {
      "name": "CpuBackend::eq_gather",
      "count": 6,
      "total_ms": 3.315959000006318,
      "self_ms": 3.0741669999957084,
      "mean_total_us": 552.6598333343863
    },
    {
      "name": "RafReduce",
      "count": 128,
      "total_ms": 2.123130999997258,
      "self_ms": 2.123130999997258,
      "mean_total_us": 16.58696093747858
    },
    {
      "name": "DoryProverState::compute_first_message",
      "count": 10,
      "total_ms": 214.79133400000632,
      "self_ms": 1.5377919999212026,
      "mean_total_us": 21479.13340000063
    },
    {
      "name": "modular_prove",
      "count": 1,
      "total_ms": 79890.35995799999,
      "self_ms": 1.3705010000020266,
      "mean_total_us": 79890359.95799999
    },
    {
      "name": "derived::product_left",
      "count": 1,
      "total_ms": 1.36775,
      "self_ms": 1.36775,
      "mean_total_us": 1367.75
    },
    {
      "name": "InstanceReduce",
      "count": 308,
      "total_ms": 6599.864421999939,
      "self_ms": 1.3211380000561477,
      "mean_total_us": 21428.131240259543
    },
    {
      "name": "derived::product_right",
      "count": 1,
      "total_ms": 1.154375,
      "self_ms": 1.154375,
      "mean_total_us": 1154.375
    },
    {
      "name": "BatchInactiveContribution",
      "count": 387,
      "total_ms": 0.8960050001367926,
      "self_ms": 0.8960050001367926,
      "mean_total_us": 2.3152583982862858
    },
    {
      "name": "Open",
      "count": 1,
      "total_ms": 1622.9312909999937,
      "self_ms": 0.7450409999936819,
      "mean_total_us": 1622931.2909999937
    },
    {
      "name": "decode",
      "count": 2,
      "total_ms": 0.7141670000000159,
      "self_ms": 0.7141670000000159,
      "mean_total_us": 357.0835000000079
    },
    {
      "name": "Materialize",
      "count": 197,
      "total_ms": 15531.58154800022,
      "self_ms": 0.5916760003194212,
      "mean_total_us": 78840.51547208233
    },
    {
      "name": "derived::extract_column",
      "count": 2,
      "total_ms": 0.5905830000042915,
      "self_ms": 0.5905830000042915,
      "mean_total_us": 295.29150000214577
    },
    {
      "name": "CheckpointEvalBatch",
      "count": 64,
      "total_ms": 0.5540020000785589,
      "self_ms": 0.5540020000785589,
      "mean_total_us": 8.656281251227483
    },
    {
      "name": "derived::rd_gather_index",
      "count": 1,
      "total_ms": 0.45395799998939035,
      "self_ms": 0.45395799998939035,
      "mean_total_us": 453.9579999893904
    },
    {
      "name": "InstanceSegmentedReduce",
      "count": 32,
      "total_ms": 21016.973460000012,
      "self_ms": 0.4473770000040531,
      "mean_total_us": 656780.4206250004
    },
    {
      "name": "pm::Witness",
      "count": 212,
      "total_ms": 0.4429640000555664,
      "self_ms": 0.4429640000555664,
      "mean_total_us": 2.089452830450785
    },
    {
      "name": "derived::hamming_weight",
      "count": 1,
      "total_ms": 0.4095,
      "self_ms": 0.4095,
      "mean_total_us": 409.5
    },
    {
      "name": "BN254::multi_pair",
      "count": 50,
      "total_ms": 732.0848719999523,
      "self_ms": 0.40533500001230277,
      "mean_total_us": 14641.697439999045
    },
    {
      "name": "BN254::multi_pair_g2_setup",
      "count": 62,
      "total_ms": 16543.135793000016,
      "self_ms": 0.40462800005823374,
      "mean_total_us": 266824.77085483895
    },
    {
      "name": "Program::trace",
      "count": 1,
      "total_ms": 6.073,
      "self_ms": 0.40279200000001586,
      "mean_total_us": 6073.0
    },
    {
      "name": "MaterializePBuffers",
      "count": 16,
      "total_ms": 0.37629300002753735,
      "self_ms": 0.37629300002753735,
      "mean_total_us": 23.518312501721084
    },
    {
      "name": "setup_emulator_with_backtraces",
      "count": 1,
      "total_ms": 0.37266700000001585,
      "self_ms": 0.37266700000001585,
      "mean_total_us": 372.66700000001583
    },
    {
      "name": "pm::Derived",
      "count": 63,
      "total_ms": 14637.665037999965,
      "self_ms": 0.36432999996468424,
      "mean_total_us": 232343.88949206294
    },
    {
      "name": "MaterializeCombinedVal",
      "count": 1,
      "total_ms": 0.33954199999570844,
      "self_ms": 0.33954199999570844,
      "mean_total_us": 339.54199999570847
    },
    {
      "name": "DoryProverState::compute_second_message",
      "count": 10,
      "total_ms": 198.39362600000203,
      "self_ms": 0.3248340000510216,
      "mean_total_us": 19839.362600000204
    },
    {
      "name": "SumcheckRound",
      "count": 19,
      "total_ms": 154.83570500000567,
      "self_ms": 0.32470800000056627,
      "mean_total_us": 8149.2476315792455
    },
    {
      "name": "DoryProverState::compute_final_message",
      "count": 1,
      "total_ms": 0.31791699999570844,
      "self_ms": 0.31791699999570844,
      "mean_total_us": 317.91699999570847
    },
    {
      "name": "mb::Transpose",
      "count": 40,
      "total_ms": 503.2948329999894,
      "self_ms": 0.313206999912858,
      "mean_total_us": 12582.370824999734
    },
    {
      "name": "CpuBackend::scale_from_host",
      "count": 1,
      "total_ms": 0.28908299998939035,
      "self_ms": 0.28908299998939035,
      "mean_total_us": 289.0829999893904
    },
    {
      "name": "AbsorbInputClaim",
      "count": 20,
      "total_ms": 0.27170700002461673,
      "self_ms": 0.27170700002461673,
      "mean_total_us": 13.585350001230836
    },
    {
      "name": "pm::R1cs",
      "count": 53,
      "total_ms": 243.55625099998713,
      "self_ms": 0.26183699998259546,
      "mean_total_us": 4595.400962263908
    },
    {
      "name": "BytecodePreprocessing::preprocess",
      "count": 1,
      "total_ms": 0.2445,
      "self_ms": 0.2445,
      "mean_total_us": 244.5
    },
    {
      "name": "mb::EqTable",
      "count": 68,
      "total_ms": 50.01561799990758,
      "self_ms": 0.23053699989616872,
      "mean_total_us": 735.523794116288
    },
    {
      "name": "Evaluate",
      "count": 248,
      "total_ms": 0.22899199994280933,
      "self_ms": 0.22899199994280933,
      "mean_total_us": 0.92335483847907
    },
    {
      "name": "ExpandingTableUpdate",
      "count": 128,
      "total_ms": 0.2226159999370575,
      "self_ms": 0.2226159999370575,
      "mean_total_us": 1.7391874995082617
    },
    {
      "name": "Squeeze",
      "count": 337,
      "total_ms": 0.2125900001190603,
      "self_ms": 0.2125900001190603,
      "mean_total_us": 0.6308308608874192
    },
    {
      "name": "EvaluatePreprocessed",
      "count": 1,
      "total_ms": 0.21125,
      "self_ms": 0.21058300000429153,
      "mean_total_us": 211.25
    },
    {
      "name": "pm::Preprocessed",
      "count": 86,
      "total_ms": 0.19516200004518033,
      "self_ms": 0.19516200004518033,
      "mean_total_us": 2.269325581920701
    },
    {
      "name": "MaterializeUnlessFresh",
      "count": 46,
      "total_ms": 9687.262167000059,
      "self_ms": 0.18866900004819034,
      "mean_total_us": 210592.6558043491
    },
    {
      "name": "derived::instruction_raf_flag",
      "count": 1,
      "total_ms": 0.16825,
      "self_ms": 0.16825,
      "mean_total_us": 168.25
    },
    {
      "name": "Preamble",
      "count": 1,
      "total_ms": 0.149125,
      "self_ms": 0.149125,
      "mean_total_us": 149.125
    },
    {
      "name": "mb::Provided",
      "count": 38,
      "total_ms": 9689.61158200001,
      "self_ms": 0.11879100008308888,
      "mean_total_us": 254989.77847368448
    },
    {
      "name": "AbsorbEvals",
      "count": 15,
      "total_ms": 0.08775100000202656,
      "self_ms": 0.08775100000202656,
      "mean_total_us": 5.85006666680177
    },
    {
      "name": "BN254::multi_pair_g1_setup",
      "count": 18,
      "total_ms": 65.11066700002551,
      "self_ms": 0.07908300003409385,
      "mean_total_us": 3617.259277779195
    },
    {
      "name": "derived::ram_val_final",
      "count": 1,
      "total_ms": 0.062875,
      "self_ms": 0.062875,
      "mean_total_us": 62.875
    },
    {
      "name": "BatchRoundFinalize",
      "count": 246,
      "total_ms": 0.05507900007814169,
      "self_ms": 0.05507900007814169,
      "mean_total_us": 0.22389837430138898
    },
    {
      "name": "ComputePower",
      "count": 200,
      "total_ms": 0.05166999997198582,
      "self_ms": 0.05166999997198582,
      "mean_total_us": 0.25834999985992907
    },
    {
      "name": "SumcheckVerifier::verify",
      "count": 2,
      "total_ms": 0.047792000010609625,
      "self_ms": 0.047792000010609625,
      "mean_total_us": 23.896000005304813
    },
    {
      "name": "MaterializeIfAbsent",
      "count": 31,
      "total_ms": 30.362749000020326,
      "self_ms": 0.04570800001174211,
      "mean_total_us": 979.443516129688
    },
    {
      "name": "prove",
      "count": 1,
      "total_ms": 1622.16875,
      "self_ms": 0.042083000004291535,
      "mean_total_us": 1622168.75
    },
    {
      "name": "mb::EqPushforward",
      "count": 5,
      "total_ms": 13.774498999997974,
      "self_ms": 0.03375100004673004,
      "mean_total_us": 2754.8997999995945
    },
    {
      "name": "InstanceBindPreviousPhase",
      "count": 3,
      "total_ms": 0.2552910000011325,
      "self_ms": 0.027039999999105932,
      "mean_total_us": 85.09700000037749
    },
    {
      "name": "mb::EqGather",
      "count": 6,
      "total_ms": 23.051915999993682,
      "self_ms": 0.02349899996817112,
      "mean_total_us": 3841.985999998947
    },
    {
      "name": "InitExpandingTable",
      "count": 16,
      "total_ms": 0.022710000038146973,
      "self_ms": 0.022710000038146973,
      "mean_total_us": 1.4193750023841858
    },
    {
      "name": "DoryScheme::open",
      "count": 1,
      "total_ms": 1622.18625,
      "self_ms": 0.0175,
      "mean_total_us": 1622186.25
    },
    {
      "name": "AliasEval",
      "count": 80,
      "total_ms": 0.017456999972462653,
      "self_ms": 0.017456999972462653,
      "mean_total_us": 0.21821249965578318
    },
    {
      "name": "CaptureScalar",
      "count": 58,
      "total_ms": 0.01637499998509884,
      "self_ms": 0.01637499998509884,
      "mean_total_us": 0.28232758594998
    },
    {
      "name": "ReleaseDevice",
      "count": 5,
      "total_ms": 0.014915999993681907,
      "self_ms": 0.014915999993681907,
      "mean_total_us": 2.9831999987363815
    },
    {
      "name": "mb::LtTable",
      "count": 2,
      "total_ms": 3.4161669999957085,
      "self_ms": 0.014001000002026557,
      "mean_total_us": 1708.0834999978542
    },
    {
      "name": "BindOpeningInputs",
      "count": 1,
      "total_ms": 0.012625,
      "self_ms": 0.012625,
      "mean_total_us": 12.625
    },
    {
      "name": "mb::EqPlusOneTable",
      "count": 2,
      "total_ms": 5.38445799998939,
      "self_ms": 0.008375,
      "mean_total_us": 2692.228999994695
    },
    {
      "name": "MaterializeSegmentedOuterEq",
      "count": 2,
      "total_ms": 0.008083000000566245,
      "self_ms": 0.008083000000566245,
      "mean_total_us": 4.041500000283122
    },
    {
      "name": "RecordEvals",
      "count": 4,
      "total_ms": 0.007916000001132488,
      "self_ms": 0.007916000001132488,
      "mean_total_us": 1.979000000283122
    },
    {
      "name": "trace_lazy",
      "count": 1,
      "total_ms": 0.3804170000000158,
      "self_ms": 0.00775,
      "mean_total_us": 380.41700000001583
    },
    {
      "name": "BeginStage",
      "count": 8,
      "total_ms": 0.003832999985665083,
      "self_ms": 0.003832999985665083,
      "mean_total_us": 0.47912499820813537
    },
    {
      "name": "InitInstanceWeights",
      "count": 1,
      "total_ms": 1.712125,
      "self_ms": 0.002625,
      "mean_total_us": 1712.125
    },
    {
      "name": "mb::ScaleByChallenge",
      "count": 1,
      "total_ms": 0.291125,
      "self_ms": 0.0016670000106096268,
      "mean_total_us": 291.125
    },
    {
      "name": "ScaleEval",
      "count": 2,
      "total_ms": 0.0014580000042915345,
      "self_ms": 0.0014580000042915345,
      "mean_total_us": 0.7290000021457672
    },
    {
      "name": "AppendDomainSeparator",
      "count": 1,
      "total_ms": 0.0012919999957084656,
      "self_ms": 0.0012919999957084656,
      "mean_total_us": 1.2919999957084656
    },
    {
      "name": "derived::iflag_right_is_imm",
      "count": 1,
      "total_ms": 0.00025,
      "self_ms": 0.00025,
      "mean_total_us": 0.25
    },
    {
      "name": "derived::iflag_left_is_rs1",
      "count": 1,
      "total_ms": 0.00025,
      "self_ms": 0.00025,
      "mean_total_us": 0.25
    },
    {
      "name": "derived::iflag_right_is_rs2",
      "count": 1,
      "total_ms": 0.000125,
      "self_ms": 0.000125,
      "mean_total_us": 0.125
    },
    {
      "name": "derived::iflag_noop",
      "count": 1,
      "total_ms": 8.400000631809235e-05,
      "self_ms": 8.400000631809235e-05,
      "mean_total_us": 0.08400000631809235
    },
    {
      "name": "derived::iflag_left_is_pc",
      "count": 1,
      "total_ms": 8.400000631809235e-05,
      "self_ms": 8.400000631809235e-05,
      "mean_total_us": 0.08400000631809235
    }
  ],
  "parent_children": {
    "Program::trace": {
      "Program::build_with_features": 1,
      "decode": 1,
      "trace": 1
    },
    "trace_lazy": {
      "setup_emulator_with_backtraces": 1
    },
    "trace": {
      "trace_lazy": 1
    },
    "BN254::multi_pair": {
      "multi_pair_parallel": 50
    },
    "modular_prove": {
      "Preamble": 1,
      "Commit": 3,
      "stage": 8
    },
    "Commit": {
      "pm::Witness": 44
    },
    "DoryScheme::commit": {
      "G1::msm": 43008,
      "BN254::multi_pair_g2_setup": 42
    },
    "BN254::multi_pair_g2_setup": {
      "multi_pair_g2_setup_parallel": 62
    },
    "multi_pair_g2_setup_parallel": {
      "DoryScheme::commit": 11
    },
    "stage": {
      "BeginStage": 8,
      "Squeeze": 337,
      "RegroupConstraints": 1,
      "Materialize": 197,
      "MaterializeIfAbsent": 31,
      "SumcheckRound": 19,
      "AbsorbRoundPoly": 265,
      "LagrangeProject": 2,
      "Evaluate": 248,
      "RecordEvals": 4,
      "AbsorbEvals": 15,
      "Bind": 176,
      "AbsorbInputClaim": 20,
      "BatchRoundBegin": 246,
      "MaterializeSegmentedOuterEq": 2,
      "MaterializeUnlessFresh": 46,
      "InstanceSegmentedReduce": 32,
      "BatchAccumulateInstance": 468,
      "BatchInactiveContribution": 387,
      "BatchRoundFinalize": 246,
      "InstanceBind": 319,
      "InstanceReduce": 308,
      "InstanceBindPreviousPhase": 3,
      "CaptureScalar": 58,
      "ReleaseDevice": 5,
      "AppendDomainSeparator": 1,
      "EvaluatePreprocessed": 1,
      "InitInstanceWeights": 1,
      "SuffixScatter": 16,
      "QBufferScatter": 16,
      "MaterializePBuffers": 16,
      "InitExpandingTable": 16,
      "ReadCheckingReduce": 128,
      "RafReduce": 128,
      "ExpandingTableUpdate": 128,
      "CheckpointEvalBatch": 64,
      "UpdateInstanceWeights": 15,
      "MaterializeRA": 1,
      "MaterializeCombinedVal": 1,
      "ComputePower": 200,
      "WeightedSum": 5,
      "AliasEval": 80,
      "ScaleEval": 2,
      "CollectOpeningClaimAt": 42,
      "ReduceOpenings": 1,
      "Open": 1,
      "BindOpeningInputs": 1
    },
    "pm::R1cs": {
      "r1cs::Az": 1,
      "r1cs::Bz": 1,
      "r1cs::Variable": 51
    },
    "RegroupConstraints": {
      "pm::R1cs": 2
    },
    "mb::EqTable": {
      "CpuBackend::eq_table": 68
    },
    "Materialize": {
      "mb::EqTable": 61,
      "mb::Provided": 2,
      "mb::EqProject": 78,
      "mb::EqPlusOneTable": 2,
      "mb::LtTable": 2,
      "mb::EqGather": 6,
      "mb::EqPushforward": 5,
      "mb::ScaleByChallenge": 1,
      "mb::Transpose": 40
    },
    "SumcheckRound": {
      "reduce_domain": 2,
      "reduce_dense": 17,
      "interpolate_inplace": 48
    },
    "Bind": {
      "pm::R1cs": 38,
      "interpolate_inplace": 14368,
      "pm::Derived": 44
    },
    "pm::Derived": {
      "derived::product_left": 1,
      "derived::product_right": 1,
      "derived::ram_combined_ra": 1,
      "derived::ram_val": 1,
      "derived::ram_ra_indicator": 2,
      "derived::ram_val_final": 1,
      "derived::extract_column": 2,
      "derived::iflag_noop": 1,
      "derived::iflag_right_is_rs2": 1,
      "derived::iflag_right_is_imm": 1,
      "derived::iflag_left_is_rs1": 1,
      "derived::iflag_left_is_pc": 1,
      "derived::reg_rs1_ra": 1,
      "derived::reg_rs2_ra": 1,
      "derived::reg_rd_wa": 1,
      "derived::reg_val": 1,
      "derived::ram_gather_index": 1,
      "derived::rd_gather_index": 1,
      "derived::lookup_table_flag": 41,
      "derived::instruction_raf_flag": 1,
      "derived::hamming_weight": 1
    },
    "mb::Provided": {
      "pm::Derived": 15,
      "mb::upload": 38,
      "pm::Witness": 6,
      "pm::R1cs": 13,
      "pm::Preprocessed": 4
    },
    "MaterializeUnlessFresh": {
      "mb::Provided": 36
    },
    "InstanceSegmentedReduce": {
      "CpuBackend::gruen_segmented_reduce": 16,
      "CpuBackend::segmented_reduce": 16
    },
    "InstanceBind": {
      "interpolate_inplace": 2978
    },
    "InstanceReduce": {
      "reduce_dense": 308
    },
    "InstanceBindPreviousPhase": {
      "interpolate_inplace": 22
    },
    "mb::EqProject": {
      "pm::Derived": 2,
      "CpuBackend::eq_project": 82,
      "pm::Witness": 80
    },
    "CpuBackend::eq_project": {
      "EqPolynomial::evals": 82
    },
    "mb::EqPlusOneTable": {
      "CpuBackend::eq_plus_one_table": 2
    },
    "EvaluatePreprocessed": {
      "pm::Preprocessed": 1
    },
    "reduce_dense": {
      "reduce_dense": 72
    },
    "mb::LtTable": {
      "CpuBackend::lt_table": 2
    },
    "InitInstanceWeights": {
      "EqPolynomial::evals": 1
    },
    "MaterializeIfAbsent": {
      "mb::EqTable": 7,
      "mb::EqProject": 4
    },
    "mb::EqGather": {
      "pm::Derived": 2,
      "CpuBackend::eq_gather": 6,
      "pm::Preprocessed": 4
    },
    "CpuBackend::eq_gather": {
      "EqPolynomial::evals": 6
    },
    "WeightedSum": {
      "pm::Preprocessed": 71
    },
    "mb::EqPushforward": {
      "pm::Preprocessed": 5,
      "CpuBackend::eq_pushforward": 5
    },
    "CpuBackend::eq_pushforward": {
      "EqPolynomial::evals": 5
    },
    "mb::ScaleByChallenge": {
      "pm::Preprocessed": 1,
      "CpuBackend::scale_from_host": 1
    },
    "mb::Transpose": {
      "pm::Witness": 40,
      "CpuBackend::transpose_from_host": 40
    },
    "CollectOpeningClaimAt": {
      "pm::Witness": 2
    },
    "ReduceOpenings": {
      "pm::Witness": 40,
      "rlc_combine": 1
    },
    "create_evaluation_proof": {
      "G1::msm": 3,
      "DoryProverState::compute_first_message": 10,
      "DoryProverState::apply_first_challenge": 10,
      "DoryProverState::compute_second_message": 10,
      "DoryProverState::apply_second_challenge": 10,
      "DoryProverState::compute_final_message": 1
    },
    "DoryProverState::compute_first_message": {
      "BN254::multi_pair_g2_setup": 20,
      "G1::msm": 12,
      "G2::msm": 10,
      "BN254::multi_pair_g1_setup": 18
    },
    "DoryProverState::compute_second_message": {
      "BN254::multi_pair": 20,
      "G1::msm": 20,
      "G2::msm": 20
    },
    "BN254::multi_pair_g1_setup": {
      "multi_pair_g1_setup_parallel": 18
    },
    "prove": {
      "create_evaluation_proof": 1
    },
    "DoryScheme::open": {
      "prove": 1
    },
    "Open": {
      "DoryScheme::open": 1
    }
  }
}